lognotify/__init__.py
lognotify/log_message.py
lognotify-0.0.4.dist-info/licenses/LICENSE
lognotify-0.0.4.dist-info/METADATA
lognotify-0.0.4.dist-info/WHEEL
lognotify-0.0.4.dist-info/top_level.txt
lognotify-0.0.4.dist-info/RECORD
