Metadata-Version: 2.4
Name: lognotify
Version: 0.0.4
Summary: A module for colorful console logging
Home-page: https://github.com/411Gamer/lognotify
Author: 411Gamer
Author-email: ponrobot0@gmail.com
License: GPL-3.0
Classifier: License :: OSI Approved :: GNU General Public License v3 (GPLv3)
License-File: LICENSE
Requires-Dist: colorama==0.4.6
Dynamic: author
Dynamic: author-email
Dynamic: classifier
Dynamic: description
Dynamic: description-content-type
Dynamic: home-page
Dynamic: license
Dynamic: license-file
Dynamic: requires-dist
Dynamic: summary
